psquare/__init__.py
psquare/psquare.py
psquare-1.1.dist-info/LICENSE
psquare-1.1.dist-info/METADATA
psquare-1.1.dist-info/WHEEL
psquare-1.1.dist-info/top_level.txt
psquare-1.1.dist-info/RECORD
