Metadata-Version: 2.1
Name: psquare
Version: 1.1
Summary: This is a Python implementation of the p-square algorithm
Home-page: https://github.com/rfrenoy/psquare
Author: Rémy Frenoy
Author-email: rfrenoy@gmail.com
License: UNKNOWN
Platform: UNKNOWN
Requires-Dist: numpy
Provides-Extra: example
Requires-Dist: matplotlib ; extra == 'example'
